setup.py
guesser/__init__.py
guesser/core.py
guesser.egg-info/PKG-INFO
guesser.egg-info/SOURCES.txt
guesser.egg-info/dependency_links.txt
guesser.egg-info/top_level.txt