Metadata-Version: 1.0
Name: guesser
Version: 0.0.1
Summary: Guesser is a library that allows you to smartly guess values to find an unkownn boundary on a function.
Home-page: https://github.com/spulec/guesser
Author: Steve Pulec
Author-email: spulec@gmail
License: UNKNOWN
Platform: UNKNOWN
